Workbook

Sheet Marketing Strategy
B1: PRESSO - DETAILED MARKETING STRATEGY & ROI PROJECTIONS
B2: Navi Mumbai Launch | Budget: Under Rs.2L/month | Starting from Zero
B4: KEY ASSUMPTIONS (Edit blue values to model scenarios)
B5: Average Order Value (AOV) | C5: 400 | D5: Based on 8-12 items per order
B6: Gross Margin on Services | C6: 0.55 | D6: After direct costs (detergent, water, electricity)
B7: Rider Cost per Order | C7: 30 | D7: Fixed payment per pickup/delivery
B8: Monthly Marketing Budget | C8: 175000 | D8: Under Rs.2L/month constraint
B9: Avg CPC - Meta Ads (Instagram/FB) | C9: 12 | D9: Navi Mumbai local targeting, service category
B10: Avg CPC - Google Ads | C10: 18 | D10: Local intent keywords: 'laundry near me'
B11: Meta Ads CTR | C11: 0.025 | D11: 2.5% CTR for local service ads
B12: Google Ads CTR | C12: 0.04 | D12: 4% CTR for high-intent search
B13: App Install-to-Order Rate | C13: 0.15 | D13: 15% of installs place first order
B14: Referral Conversion Rate | C14: 0.3 | D14: 30% of referred users order
B15: Repeat Order Rate (Monthly) | C15: 0.45 | D15: 45% of customers reorder within 30 days
B16: Avg Orders per Repeat Customer/Month | C16: 1.8 | D16: Frequency of repeat customers
... B18: CAC Benchmark (Industry) | C18: 750 | D18: Rs.600-850 for laundry apps in India
B20: MONTHLY CHANNEL BUDGET BREAKDOWN (Month 1-3: Launch Phase)
B21: Channel | C21: Monthly Budget | D21: % of Total | E21: Est. New Customers | F21: Cost per Customer | G21: Strategy & Tactics
B22: Instagram Reels + Stories | C22: 35000 | D22: =C22/C30 -> 0.2 | E22: =C22/C9*C13 -> 437.5 | F22: =IF(E22>0,C22/E22,"-") -> 80 | G22: Short-form video content: before/after laundry transformations, 'Day in life of Presso rider', Navi Mumbai lifestyle content. 3-4 Reels/week. Boost top performers.
B23: Meta Paid Ads (FB + IG) | C23: 45000 | D23: =C23/C30 -> 0.25714286 | E23: =C23/C9*C13 -> 562.5 | F23: =IF(E23>0,C23/E23,"-") -> 80 | G23: Location-targeted ads to Kharghar, Vashi, Belapur pin codes. Carousel ads showing services + pricing. Retarget app installers who haven't ordered.
B24: Google Search Ads | C24: 35000 | D24: =C24/C30 -> 0.2 | E24: =C24/C10*C13 -> 291.66667 | F24: =IF(E24>0,C24/E24,"-") -> 120 | G24: High-intent keywords: 'laundry delivery Navi Mumbai', 'dry cleaning Kharghar', 'wash and fold near me'. Call extensions + app install campaigns.
B25: WhatsApp Marketing | C25: 10000 | D25: =C25/C30 -> 0.057142857 | E25: 15 | F25: =IF(E25>0,C25/E25,"-") -> 666.66667 | G25: Broadcast lists for offers, order confirmations, referral nudges. WhatsApp Business catalog. Society group partnerships.
B26: Referral Program (Coins) | C26: 20000 | D26: =C26/C30 -> 0.11428571 | E26: =C26/C17*C14 -> 60 | F26: =IF(E26>0,C26/E26,"-") -> 333.33333 | G26: In-app referral: both sides earn Rs.50 in Presso Coins. Track via unique codes. Budget = coin redemption subsidy for ~200 referral conversions.
B27: Hyperlocal (Flyers/Banners) | C27: 15000 | D27: =C27/C30 -> 0.085714286 | E27: 12 | F27: =IF(E27>0,C27/E27,"-") -> 1250 | G27: Society gate standees in top 10 complexes. Door-to-door flyers with QR code. Local shop cross-promotion. Refresh monthly.
B28: Influencer Micro-Collabs | C28: 10000 | D28: =C28/C30 -> 0.057142857 | E28: 8 | F28: =IF(E28>0,C28/E28,"-") -> 1250 | G28: 2-3 Navi Mumbai micro-influencers/month (5K-20K followers). Free service + Rs.3-5K per post. Focus: lifestyle, parenting, student creators.
B29: Content & SEO | C29: 5000 | D29: =C29/C30 -> 0.028571429 | E29: 5 | F29: =IF(E29>0,C29/E29,"-") -> 1000 | G29: Google My Business optimization, blog posts on garment care, Instagram carousels. Organic long-term play.
B30: TOTAL MONTHLY BUDGET | C30: =SUM(C22:C29) -> 175000 | D30: 1 | E30: =SUM(E22:E29) -> 1391.6667 | F30: =IF(E30>0,C30/E30,0) -> 125.7485 | G30: Blended CAC across all channels

Sheet 12-Month Projections
B1: PRESSO - 12-MONTH MARKETING ROI & FINANCIAL PROJECTIONS
B3: METRIC | C3: Month 1 | D3: Month 2 | E3: Month 3 | F3: Month 4 | G3: Month 5 | H3: Month 6 | I3: Month 7 | J3: Month 8 | K3: Month 9 | L3: Month 10 | M3: Month 11 | N3: Month 12 | O3: YEAR 1 TOTAL
B4: MARKETING INVESTMENT
B5: Total Marketing Spend | C5: 125000 | D5: 150000 | E5: 175000 | F5: 175000 | G5: 190000 | H5: 190000 | I5: 175000 | J5: 160000 | K5: 150000 | L5: 150000 | M5: 140000 | N5: 130000 | O5: =SUM(C5:N5) -> 1910000
B6: Launch Campaign (One-Time) | C6: 75000 | D6: 25000 | E6: 0 | F6: 0 | G6: 0 | H6: 0 | I6: 0 | J6: 0 | K6: 0 | L6: 0 | M6: 0 | N6: 0 | O6: =SUM(C6:N6) -> 100000
B7: TOTAL MARKETING COST | C7: =C5+C6 -> 200000 | D7: =D5+D6 -> 175000 | E7: =E5+E6 -> 175000 | F7: =F5+F6 -> 175000 | G7: =G5+G6 -> 190000 | H7: =H5+H6 -> 190000 | I7: =I5+I6 -> 175000 | J7: =J5+J6 -> 160000 | ... N7: =N5+N6 -> 130000 | O7: =SUM(C7:N7) -> 2010000
B9: CUSTOMER ACQUISITION
B10: New Customers (Paid Channels) | C10: 40 | D10: 55 | E10: 70 | F10: 80 | G10: 95 | H10: 100 | I10: 95 | J10: 90 | K10: 85 | L10: 85 | M10: 80 | N10: 75 | O10: =SUM(C10:N10) -> 950
B11: New Customers (Referrals) | C11: 5 | D11: =ROUND(C14*0.08,0) -> 4 | E11: =ROUND(D14*0.08,0) -> 10 | F11: =ROUND(E14*0.08,0) -> 18 | G11: =ROUND(F14*0.08,0) -> 27 | H11: =ROUND(G14*0.08,0) -> 39 | I11: =ROUND(H14*0.08,0) -> 52 | J11: =ROUND(I14*0.08,0) -> 67 | K11: =ROUND(J14*0.08,0) -> 83 | ... N11: =ROUND(M14*0.08,0) -> 139 | O11: =SUM(C11:N11) -> 662
B12: New Customers (Organic/WOM) | C12: 8 | D12: 12 | E12: 15 | F12: 20 | G12: 25 | H12: 30 | I12: 35 | J12: 40 | K12: 45 | L12: 50 | M12: 55 | N12: 60 | O12: =SUM(C12:N12) -> 395
B13: Total New Customers | C13: =C10+C11+C12 -> 53 | D13: =D10+D11+D12 -> 71 | E13: =E10+E11+E12 -> 95 | F13: =F10+F11+F12 -> 118 | G13: =G10+G11+G12 -> 147 | H13: =H10+H11+H12 -> 169 | I13: =I10+I11+I12 -> 182 | J13: =J10+J11+J12 -> 197 | ... N13: =N10+N11+N12 -> 274 | O13: =SUM(C13:N13) -> 2007
B14: Cumulative Customer Base | C14: =C13 -> 53 | D14: =C14+D13 -> 124 | E14: =D14+E13 -> 219 | F14: =E14+F13 -> 337 | G14: =F14+G13 -> 484 | H14: =G14+H13 -> 653 | I14: =H14+I13 -> 835 | J14: =I14+J13 -> 1032 | K14: =J14+K13 -> 1245 | ... N14: =M14+N13 -> 2007 | O14: =N14 -> 2007
B15: Blended CAC (Cost per New Customer) | C15: =IF(C13>0,C7/C13,0) -> 3773.5849 | D15: =IF(D13>0,D7/D13,0) -> 2464.7887 | E15: =IF(E13>0,E7/E13,0) -> 1842.1053 | F15: =IF(F13>0,F7/F13,0) -> 1483.0508 | G15: =IF(G13>0,G7/G13,0) -> 1292.517 | H15: =IF(H13>0,H7/H13,0) -> 1124.2604 | I15: =IF(I13>0,I7/I13,0) -> 961.53846 | J15: =IF(J13>0,J7/J13,0) -> 812.18274 | ... O15: =IF(O13>0,O7/O13,0) -> 1001.4948
B17: ORDERS & REVENUE
B18: First-Time Orders | C18: =C13 -> 53 | D18: =D13 -> 71 | E18: =E13 -> 95 | F18: =F13 -> 118 | G18: =G13 -> 147 | H18: =H13 -> 169 | I18: =I13 -> 182 | J18: =J13 -> 197 | ... N18: =N13 -> 274 | O18: =SUM(C18:N18) -> 2007
B19: Repeat Orders | C19: 0 | D19: =ROUND(C14*'Marketing Strategy'!$C$15*'Marketing Strategy'!$C$16,0) -> 43 | E19: =ROUND(D14*'Marketing Strategy'!$C$15*'Marketing Strategy'!$C$16,0) -> 100 | F19: =ROUND(E14*'Marketing Strategy'!$C$15*'Marketing Strategy'!$C$16,0) -> 177 | G19: =ROUND(F14*'Marketing Strategy'!$C$15*'Marketing Strategy'!$C$16,0) -> 273 | H19: =ROUND(G14*'Marketing Strategy'!$C$15*'Marketing Strategy'!$C$16,0) -> 392 | I19: =ROUND(H14*'Marketing Strategy'!$C$15*'Marketing Strategy'!$C$16,0) -> 529 | J19: =ROUND(I14*'Marketing Strategy'!$C$15*'Marketing Strategy'!$C$16,0) -> 676 | K19: =ROUND(J14*'Marketing Strategy'!$C$15*'Marketing Strategy'!$C$16,0) -> 836 | ... N19: =ROUND(M14*'Marketing Strategy'!$C$15*'Marketing Strategy'!$C$16,0) -> 1404 | O19: =SUM(C19:N19) -> 6637
B20: TOTAL ORDERS | C20: =C18+C19 -> 53 | D20: =D18+D19 -> 114 | E20: =E18+E19 -> 195 | F20: =F18+F19 -> 295 | G20: =G18+G19 -> 420 | H20: =H18+H19 -> 561 | I20: =I18+I19 -> 711 | J20: =J18+J19 -> 873 | ... N20: =N18+N19 -> 1678 | O20: =SUM(C20:N20) -> 8644
B21: Gross Revenue | C21: =C20*'Marketing Strategy'!$C$5 -> 21200 | D21: =D20*'Marketing Strategy'!$C$5 -> 45600 | E21: =E20*'Marketing Strategy'!$C$5 -> 78000 | F21: =F20*'Marketing Strategy'!$C$5 -> 118000 | G21: =G20*'Marketing Strategy'!$C$5 -> 168000 | H21: =H20*'Marketing Strategy'!$C$5 -> 224400 | I21: =I20*'Marketing Strategy'!$C$5 -> 284400 | J21: =J20*'Marketing Strategy'!$C$5 -> 349200 | ... N21: =N20*'Marketing Strategy'!$C$5 -> 671200 | O21: =SUM(C21:N21) -> 3457600
B22: Gross Profit (after COGS) | C22: =C21*'Marketing Strategy'!$C$6-C20*'Marketing Strategy'!$C$7 -> 10070 | D22: =D21*'Marketing Strategy'!$C$6-D20*'Marketing Strategy'!$C$7 -> 21660 | E22: =E21*'Marketing Strategy'!$C$6-E20*'Marketing Strategy'!$C$7 -> 37050 | F22: =F21*'Marketing Strategy'!$C$6-F20*'Marketing Strategy'!$C$7 -> 56050 | G22: =G21*'Marketing Strategy'!$C$6-G20*'Marketing Strategy'!$C$7 -> 79800 | H22: =H21*'Marketing Strategy'!$C$6-H20*'Marketing Strategy'!$C$7 -> 106590 | I22: =I21*'Marketing Strategy'!$C$6-I20*'Marketing Strategy'!$C$7 -> 135090 | J22: =J21*'Marketing Strategy'!$C$6-J20*'Marketing Strategy'!$C$7 -> 165870 | ... N22: =N21*'Marketing Strategy'!$C$6-N20*'Marketing Strategy'!$C$7 -> 318820 | O22: =SUM(C22:N22) -> 1642360
B24: PROFITABILITY ANALYSIS
B25: Fixed Ops (Rent, Staff, Tech) | C25: 110000 | D25: 110000 | E25: 115000 | F25: 120000 | G25: 125000 | H25: 130000 | I25: 135000 | J25: 140000 | K25: 145000 | L25: 150000 | M25: 155000 | N25: 160000 | O25: =SUM(C25:N25) -> 1595000
B26: NET PROFIT / (LOSS) | C26: =C22-C7-C25 -> -299930 | D26: =D22-D7-D25 -> -263340 | E26: =E22-E7-E25 -> -252950 | F26: =F22-F7-F25 -> -238950 | G26: =G22-G7-G25 -> -235200 | H26: =H22-H7-H25 -> -213410 | I26: =I22-I7-I25 -> -174910 | J26: =J22-J7-J25 -> -134130 | ... N26: =N22-N7-N25 -> 28820 | O26: =SUM(C26:N26) -> -1962640
B27: Cumulative P&L | C27: =C26 -> -299930 | D27: =C27+D26 -> -563270 | E27: =D27+E26 -> -816220 | F27: =E27+F26 -> -1055170 | G27: =F27+G26 -> -1290370 | H27: =G27+H26 -> -1503780 | I27: =H27+I26 -> -1678690 | J27: =I27+J26 -> -1812820 | K27: =J27+K26 -> -1908510 | ... N27: =M27+N26 -> -1962640 | O27: =N27 -> -1962640
B28: Marketing ROI % | C28: =IF(C7>0,(C21-C7)/C7,0) -> -0.894 | D28: =IF(D7>0,(D21-D7)/D7,0) -> -0.73942857 | E28: =IF(E7>0,(E21-E7)/E7,0) -> -0.55428571 | F28: =IF(F7>0,(F21-F7)/F7,0) -> -0.32571429 | G28: =IF(G7>0,(G21-G7)/G7,0) -> -0.11578947 | H28: =IF(H7>0,(H21-H7)/H7,0) -> 0.18105263 | I28: =IF(I7>0,(I21-I7)/I7,0) -> 0.62514286 | J28: =IF(J7>0,(J21-J7)/J7,0) -> 1.1825 | ... O28: =IF(O7>0,(O21-O7)/O7,0) -> 0.720199
B30: KEY METRICS
B31: Revenue per Marketing Rupee | C31: =IF(C7>0,C21/C7,0) -> 0.106 | D31: =IF(D7>0,D21/D7,0) -> 0.26057143 | E31: =IF(E7>0,E21/E7,0) -> 0.44571429 | F31: =IF(F7>0,F21/F7,0) -> 0.67428571 | G31: =IF(G7>0,G21/G7,0) -> 0.88421053 | H31: =IF(H7>0,H21/H7,0) -> 1.1810526 | I31: =IF(I7>0,I21/I7,0) -> 1.6251429 | J31: =IF(J7>0,J21/J7,0) -> 2.1825 | ... O31: =IF(O7>0,O21/O7,0) -> 1.720199
B32: Orders per Customer (Monthly) | C32: =IF(C14>0,C20/C14,0) -> 1 | D32: =IF(D14>0,D20/D14,0) -> 0.91935484 | E32: =IF(E14>0,E20/E14,0) -> 0.89041096 | F32: =IF(F14>0,F20/F14,0) -> 0.87537092 | G32: =IF(G14>0,G20/G14,0) -> 0.8677686 | H32: =IF(H14>0,H20/H14,0) -> 0.85911179 | I32: =IF(I14>0,I20/I14,0) -> 0.85149701 | J32: =IF(J14>0,J20/J14,0) -> 0.84593023 | ... O32: =IF(O14>0,O20/O14,0) -> 4.3069258

Sheet 8-Week Launch Plan
B1: PRESSO - WEEK-BY-WEEK LAUNCH MARKETING PLAN
B3: Week | C3: Activity | D3: Budget (Rs.) | E3: Expected Outcome | F3: Owner / Notes
B4: PRE-LAUNCH PHASE
B5: Week 1 | C5: Set up Instagram, Google My Business, WhatsApp Business | D5: 5,000 | E5: Profiles live, 50 initial followers | F5: Create content calendar, branding templates
B6: Week 1 | C6: Design flyers, QR code standees, society banners | D6: 8,000 | E6: Marketing collateral ready | F6: Print 500 flyers, 10 standees
B7: Week 2 | C7: Content creation: 10 Reels + 15 Stories stockpile | D7: 10,000 | E7: 2 weeks of content ready | F7: Before/after, how-it-works, pricing explainers
B8: Week 2 | C8: WhatsApp community building in target societies | D8: 3,000 | E8: 100-150 pre-launch sign-ups | F8: Kharghar, Vashi, Belapur housing societies
B9: Week 2 | C9: Identify 5 micro-influencers, negotiate collabs | D9: 0 | E9: 5 influencers confirmed | F9: Free service + Rs.3-5K per post/reel
B10: LAUNCH WEEK
B11: Week 3 | C11: APP LAUNCH: 'First Order Free Delivery' campaign | D11: 25,000 | E11: 50-75 app installs, 15-25 orders | F11: Heavy social push, WhatsApp blast, society flyers
B12: Week 3 | C12: Meta Ads: Location-targeted carousel + video ads | D12: 15,000 | E12: 10,000-15,000 impressions, 200+ clicks | F12: Pin code targeting: Kharghar, Vashi, Belapur
B13: Week 3 | C13: Google Ads: 'laundry delivery Navi Mumbai' keywords | D13: 10,000 | E13: 150-250 clicks, 20-35 installs | F13: Start with exact match, expand to broad
B14: Week 3 | C14: Distribute flyers in top 5 residential complexes | D14: 5,000 | E14: 500 flyers distributed, QR scans tracked | F14: Morning 8-10 AM gate placement
B15: Week 4 | C15: Influencer posts go live (3 of 5 creators) | D15: 15,000 | E15: 5,000-15,000 organic reach | F15: Track UTM links per influencer
B16: Week 4 | C16: Activate referral program: Rs.50 coins each side | D16: 10,000 | E16: 15-25 referral sign-ups | F16: In-app prompt after first order
B17: Week 4 | C17: Retarget app installers who haven't ordered | D17: 8,000 | E17: 5-10% conversion of non-ordering installs | F17: Meta retargeting pixel
B18: EARLY GROWTH PHASE
B19: Week 5 | C19: Scale Meta Ads to best-performing creatives | D19: 20,000 | E19: 300+ clicks, 45-60 installs | F19: Kill underperforming ads, double winners
B20: Week 5 | C20: Student outreach: college notice boards, PG tie-ups | D20: 5,000 | E20: 20-30 student sign-ups | F20: Student verification = 10% discount
B21: Week 6 | C21: Remaining 2 influencer posts + UGC reshare campaign | D21: 8,000 | E21: Customer testimonials as content | F21: Repost customer stories, reviews
B22: Week 6 | C22: Expand Google Ads: add 'dry cleaning', 'iron near me' | D22: 12,000 | E22: Broaden keyword coverage | F22: Monitor quality score, adjust bids
B23: Week 7 | C23: WhatsApp offer blast: 'Order 3, Get 4th Free' | D23: 5,000 | E23: Re-activate dormant first-time customers | F23: Segment: ordered once, not reordered
B24: Week 7 | C24: Expand flyer coverage to 5 more societies | D24: 7,000 | E24: Another 500 flyers, new area coverage | F24: Seawoods, Ulwe, Panvel areas
B25: Week 8 | C25: Review all channel performance, optimize budget split | D25: 5,000 | E25: Data-driven budget reallocation | F25: Double down on best CAC channels
B26: Week 8 | C26: Set up Google Search Console, blog first 2 articles | D26: 3,000 | E26: SEO foundation laid | F26: Target: 'laundry tips', 'garment care'
B27: TOTAL 8-WEEK LAUNCH BUDGET | D27: Rs.2,04,000 | E27: 100-175 total customers acquired

Sheet ROI Scenarios
B1: PRESSO - ROI SCENARIO ANALYSIS
B2: What happens if things go better or worse than planned?
B4: Metric (Year 1) | C4: Conservative | D4: Base Case | E4: Optimistic
B5: Total Marketing Spend (Year 1) | C5: 1500000 | D5: 1910000 | E5: 2200000
B6: Total New Customers (Year 1) | C6: 500 | D6: 950 | E6: 1400
B7: Blended CAC | C7: 3000 | D7: 2010 | E7: 1571
B8: Repeat Rate (Monthly) | C8: 0.3 | D8: 0.45 | E8: 0.55
B9: Total Orders (Year 1) | C9: 1200 | D9: 3800 | E9: 6500
B10: Average Order Value | C10: 350 | D10: 400 | E10: 450
B11: Gross Revenue (Year 1) | C11: 420000 | D11: 1520000 | E11: 2925000
B12: Gross Profit (55% margin - rider) | C12: 189000 | D12: 684000 | E12: 1316250
B13: Fixed Operating Costs (Year 1) | C13: 1595000 | D13: 1595000 | E13: 1595000
B14: NET PROFIT / (LOSS) Year 1 | C14: -2906000 | D14: -2321000 | E14: -1478750
B16: Break-Even Month | C16: Month 14-16 | D16: Month 10-12 | E16: Month 7-8
B17: 12-Month Customer LTV | C17: 2520 | D17: 3888 | E17: 5940
B18: LTV : CAC Ratio | C18: 0.8x | D18: 1.9x | E18: 3.8x
B19: Monthly Revenue at Month 12 | C19: 210000 | D19: 600000 | E19: 1170000
B20: Marketing ROI at Month 12 | C20: -50% | D20: 150% | E20: 400%
B22: KEY INSIGHT
B23: Year 1 will be a net loss in ALL scenarios. This is normal for a startup in growth mode. The question is how fast you reach break-even.
B24: The single biggest lever is REPEAT RATE. Going from 30% to 55% monthly repeat doubles your Year 1 revenue with the same marketing spend.
B25: At Rs.2L/month budget, you're acquisition-constrained. Every Rs.1 spent on retention (loyalty, service quality, app experience) has 3-5x more impact than Rs.1 on acquisition.
B26: Target: Keep blended CAC under Rs.2,500 and repeat rate above 40%. If you hit both, break-even is achievable by Month 10-12.
B27: Referrals are your cheapest channel at ~Rs.100/customer vs Rs.750+ for paid ads. Invest heavily in making the referral experience frictionless.
